lycoris/__init__.py
lycoris/config.py
lycoris/config_sdk.py
lycoris/kohya.py
lycoris/logging.py
lycoris/wrapper.py
lycoris/functional/__init__.py
lycoris/functional/boft.py
lycoris/functional/diag_oft.py
lycoris/functional/general.py
lycoris/functional/locon.py
lycoris/functional/loha.py
lycoris/functional/lokr.py
lycoris/modules/__init__.py
lycoris/modules/base.py
lycoris/modules/boft.py
lycoris/modules/diag_oft.py
lycoris/modules/dylora.py
lycoris/modules/full.py
lycoris/modules/glora.py
lycoris/modules/ia3.py
lycoris/modules/locon.py
lycoris/modules/loha.py
lycoris/modules/lokr.py
lycoris/modules/norms.py
lycoris/utils/__init__.py
lycoris/utils/general.py
lycoris/utils/logger.py
lycoris/utils/preset.py
lycoris/utils/quant.py
lycoris/utils/xformers_utils.py
lycoris_lora-3.4.0.dist-info/licenses/LICENSE.md
test/__init__.py
test/compile.py
test/compile_swap_err_minimal_rep.py
test/functional.py
test/kohya.py
test/module.py
test/precision_merge_test.py
test/restore.py
test/wrapper.py
lycoris_lora-3.4.0.dist-info/METADATA
lycoris_lora-3.4.0.dist-info/WHEEL
lycoris_lora-3.4.0.dist-info/top_level.txt
lycoris_lora-3.4.0.dist-info/RECORD
